{
  "$schema": "https://schema.management.azure.com/schemas/2015-01-01/deploymentTemplate.json",
  "contentVersion": "1.0.0.0",
  "parameters": {
    "name": {
      "type": "string"
  },
    "endpoints": {
      "type": "array",
      "metadata": {
          "description": "An additional hostname this application should be accessible on"
      }
    }
  },
  "resources": [
    {
      "apiVersion": "2018-04-01",
      "type": "Microsoft.Network/trafficManagerProfiles/ExternalEndpoints",
      "location": "global",
      "name": "[concat(parameters('name'), '/', parameters('endpoints')[copyIndex()].name)]",
      "copy": {
        "name": "endpointloop",
        "count": "[length(parameters('endpoints'))]"
      },
      "properties": {
        "target": "[parameters('endpoints')[copyIndex()].target]",
        "priority": "[parameters('endpoints')[copyIndex()].priority]",
        "endpointStatus": "Enabled",
        "customHeaders": [
          {
            "name": "Host",
            "value": "[parameters('endpoints')[copyIndex()].hostHeader]"
          }
        ]
      }
    }
  ]
}